halva/__init__.py
halva/inference.py
halva-0.1.1.dist-info/METADATA
halva-0.1.1.dist-info/WHEEL
halva-0.1.1.dist-info/licenses/LICENSE.txt
halva-0.1.1.dist-info/RECORD
